Metadata-Version: 1.0
Name: sid-first-pack
Version: 0.0.5
Summary: Sid First Package
Home-page: UNKNOWN
Author: Sid-ISQ
Author-email: gmcovas@isq.pt
License: UNKNOWN
Platform: UNKNOWN
